trano/__init__.py
trano/data/default.yaml
trano/data/include.py
trano/data_models/__init__.py
trano/data_models/conversion.py
trano/data_models/converter.py
trano/data_models/parameters.yaml
trano/data_models/trano.yaml
trano/data_models/trano_final.yaml
trano/elements/__init__.py
trano/elements/base.py
trano/elements/boundary.py
trano/elements/bus.py
trano/elements/common_base.py
trano/elements/config/containers.yaml
trano/elements/connection.py
trano/elements/construction.py
trano/elements/containers.py
trano/elements/control.py
trano/elements/data_bus/__init__.py
trano/elements/data_bus/controller_bus.py
trano/elements/data_bus/inputs.py
trano/elements/envelope.py
trano/elements/figure.py
trano/elements/library/__init__.py
trano/elements/library/base.py
trano/elements/library/components.py
trano/elements/library/library.json
trano/elements/library/library.py
trano/elements/library/models/buildings/internal_element.yaml
trano/elements/library/models/buildings/space.yaml
trano/elements/library/models/buildings/weather.yaml
trano/elements/library/models/default/ahu_control.yaml
trano/elements/library/models/default/air_handling_unit.yaml
trano/elements/library/models/default/boiler.yaml
trano/elements/library/models/default/boiler_control.yaml
trano/elements/library/models/default/boundary.yaml
trano/elements/library/models/default/collector_control.yaml
trano/elements/library/models/default/data_bus.yaml
trano/elements/library/models/default/duct.yaml
trano/elements/library/models/default/emission_control.yaml
trano/elements/library/models/default/heat_meter.yaml
trano/elements/library/models/default/occupancy.yaml
trano/elements/library/models/default/photovoltaic.yaml
trano/elements/library/models/default/pump.yaml
trano/elements/library/models/default/radiator.yaml
trano/elements/library/models/default/split_valve.yaml
trano/elements/library/models/default/temperature_sensor.yaml
trano/elements/library/models/default/three_way_valve.yaml
trano-0.13.0.dist-info/METADATA
trano-0.13.0.dist-info/WHEEL
trano-0.13.0.dist-info/entry_points.txt
trano-0.13.0.dist-info/licenses/LICENSE
trano-0.13.0.dist-info/RECORD
