Metadata-Version: 2.4
Name: trano
Version: 0.13.0
Summary: 
License-File: LICENSE
Keywords: energy simulation,modelica,interoperability,building energy simulation,buildings,ideas
Author: Ando Andriamamonjy
Author-email: andoludovic.andriamamonjy@gmail.com
Requires-Python: >=3.10,<4.0
Classifier: Intended Audience :: Developers
Classifier: License :: OSI Approved :: GNU General Public License v3 (GPLv3)
Classifier: Programming Language :: Python
Classifier: Programming Language :: Python :: 3
Classifier: Programming Language :: Python :: 3.10
Classifier: Programming Language :: Python :: 3.11
Classifier: Programming Language :: Python :: 3.12
Classifier: Programming Language :: Python :: 3.13
Classifier: Programming Language :: Python :: 3.14
Classifier: Programming Language :: Python :: 3 :: Only
Classifier: Programming Language :: Python :: 3.9
Classifier: Typing :: Typed
Requires-Dist: buildingspy (>=5.1.0,<6.0.0)
Requires-Dist: docker (>=7.0.0,<8.0.0)
Requires-Dist: jinja2 (>=3.1.2,<4.0.0)
Requires-Dist: linkml (>=1.8.1,<2.0.0)
Requires-Dist: networkx (>=3.2.1,<4.0.0)
Requires-Dist: pandas (>=2.2.2,<3.0.0)
Requires-Dist: plotly (>=5.22.0,<6.0.0)
Requires-Dist: pydantic (==2.8.0)
Requires-Dist: pydot (>=3.0.4,<4.0.0)
Requires-Dist: python-docx (>=1.1.2,<2.0.0)
Requires-Dist: pyyaml-include (>=2.1,<3.0)
Requires-Dist: typer (>=0.19.2,<0.20.0)
Requires-Dist: uuid (>=1.30,<2.0)
Requires-Dist: yattag (>=1.16.1,<2.0.0)
Project-URL: Homepage, https://andoludo.github.io/trano/
Project-URL: Repository, https://github.com/andoludo/trano
